cryoten/__init__.py
cryoten/bibtex.py
cryoten/constants.py
cryoten/icon.png
cryoten/protocols.conf
cryoten/protocols/__init__.py
cryoten/protocols/protocol_cryoten.py
cryoten/tests/__init__.py
cryoten/tests/tests_cryoten.py
cryoten/viewers/__init__.py
cryoten/wizards/__init__.py
cryoten/wizards/wizard_hello_world.py
scipion_em_cryoten-1.0.0.dist-info/LICENSE
scipion_em_cryoten-1.0.0.dist-info/LICENSE.txt
scipion_em_cryoten-1.0.0.dist-info/METADATA
scipion_em_cryoten-1.0.0.dist-info/WHEEL
scipion_em_cryoten-1.0.0.dist-info/entry_points.txt
scipion_em_cryoten-1.0.0.dist-info/top_level.txt
scipion_em_cryoten-1.0.0.dist-info/RECORD
