Metadata-Version: 2.1
Name: scipion-em-cryoten
Version: 1.0.0
Summary: Cryoten plugin for Scipion
Home-page: https://github.com/scipion-em/scipion-em-cryoten
Author: Javier Sanchez
Author-email: scipion@cnb.csic.es
Project-URL: Bug Reports, https://github.com/scipion-em/scipion-em-cryoten/issues
Project-URL: Source, https://github.com/scipion-em/scipion-em-cryoten/
Keywords: scipion cryoem imageprocessing scipion-3.0 datasimulation
License-File: LICENSE
License-File: LICENSE.txt
Requires-Dist: scipion-pyworkflow
Requires-Dist: scipion-em
